brainglobe_utils/__init__.py
brainglobe_utils/napari.yaml
brainglobe_utils/IO/__init__.py
brainglobe_utils/IO/cells.py
brainglobe_utils/IO/surfaces.py
brainglobe_utils/IO/yaml.py
brainglobe_utils/IO/image/__init__.py
brainglobe_utils/IO/image/load.py
brainglobe_utils/IO/image/save.py
brainglobe_utils/IO/image/utils.py
brainglobe_utils/brainmapper/__init__.py
brainglobe_utils/brainmapper/analysis.py
brainglobe_utils/brainmapper/export.py
brainglobe_utils/brainmapper/transform_widget.py
brainglobe_utils/brainreg/__init__.py
brainglobe_utils/brainreg/transform.py
brainglobe_utils/cells/__init__.py
brainglobe_utils/cells/cells.py
brainglobe_utils/citation/__init__.py
brainglobe_utils/citation/bibtex_fmt.py
brainglobe_utils/citation/cite.py
brainglobe_utils/citation/fetch.py
brainglobe_utils/citation/format.py
brainglobe_utils/citation/repositories.py
brainglobe_utils/citation/text_fmt.py
brainglobe_utils/general/__init__.py
brainglobe_utils/general/config.py
brainglobe_utils/general/exceptions.py
brainglobe_utils/general/list.py
brainglobe_utils/general/logging.py
brainglobe_utils/general/numerical.py
brainglobe_utils/general/pathlib.py
brainglobe_utils/general/string.py
brainglobe_utils/general/system.py
brainglobe_utils/image/__init__.py
brainglobe_utils/image/binning.py
brainglobe_utils/image/heatmap.py
brainglobe_utils/image/masking.py
brainglobe_utils/image/scale.py
brainglobe_utils/pandas/__init__.py
brainglobe_utils/pandas/misc.py
brainglobe_utils/qtpy/__init__.py
brainglobe_utils/qtpy/brainglobe.png
brainglobe_utils/qtpy/logo.py
brainglobe_utils-0.10.0.dist-info/licenses/LICENSE
brainglobe_utils-0.10.0.dist-info/METADATA
brainglobe_utils-0.10.0.dist-info/WHEEL
brainglobe_utils-0.10.0.dist-info/entry_points.txt
brainglobe_utils-0.10.0.dist-info/top_level.txt
brainglobe_utils-0.10.0.dist-info/RECORD
