Metadata-Version: 2.4
Name: brainglobe-utils
Version: 0.10.0
Summary: Shared general purpose tools for the BrainGlobe project
Author-email: Adam Tyson <code@adamltyson.com>
License: MIT License
Project-URL: homepage, https://brainglobe.info
Project-URL: bug_tracker, https://github.com/brainglobe/brainglobe-utils/issues
Project-URL: source_code, https://github.com/brainglobe/brainglobe-utils
Project-URL: user_support, https://github.com/brainglobe/brainglobe-utils/issues
Classifier: Development Status :: 3 - Alpha
Classifier: Framework :: napari
Classifier: Intended Audience :: Developers
Classifier: Intended Audience :: Science/Research
Classifier: Operating System :: OS Independent
Classifier: Programming Language :: Python
Classifier: Programming Language :: Python :: 3
Classifier: Programming Language :: Python :: 3.11
Classifier: Programming Language :: Python :: 3.12
Classifier: Programming Language :: Python :: 3.13
Requires-Python: >=3.11
License-File: LICENSE
Requires-Dist: brainglobe-atlasapi>=2.0.1
Requires-Dist: brainglobe-space
Requires-Dist: configobj
Requires-Dist: natsort
Requires-Dist: nibabel>=2.1.0
Requires-Dist: numba
Requires-Dist: numpy
Requires-Dist: dask
Requires-Dist: pandas
Requires-Dist: psutil
Requires-Dist: pyarrow
Requires-Dist: PyYAML
Requires-Dist: scikit-image
Requires-Dist: scipy
Requires-Dist: slurmio
Requires-Dist: tifffile
Requires-Dist: tqdm
Requires-Dist: qt-niu
Requires-Dist: rapidyaml
Provides-Extra: qt
Requires-Dist: qtpy; extra == "qt"
Requires-Dist: superqt; extra == "qt"
Provides-Extra: napari
Requires-Dist: brainglobe-utils[qt]; extra == "napari"
Requires-Dist: napari[all]; extra == "napari"
Provides-Extra: dev
Requires-Dist: black; extra == "dev"
Requires-Dist: coverage; extra == "dev"
Requires-Dist: mypy; extra == "dev"
Requires-Dist: pre-commit; extra == "dev"
Requires-Dist: pyqt5; extra == "dev"
Requires-Dist: pytest-cov; extra == "dev"
Requires-Dist: pytest-qt; extra == "dev"
Requires-Dist: pytest-mock; extra == "dev"
Requires-Dist: pytest; extra == "dev"
Requires-Dist: ruff; extra == "dev"
Requires-Dist: scikit-image; extra == "dev"
Requires-Dist: setuptools_scm; extra == "dev"
Requires-Dist: tox; extra == "dev"
Requires-Dist: pooch; extra == "dev"
Requires-Dist: brainglobe-utils[napari]; extra == "dev"
Dynamic: license-file
